paxtual/DFTable.py
paxtual/E700VaultLabels.py
paxtual/SingleTermDetailsScreen.py
paxtual/TI_Input.py
paxtual/__about__.py
paxtual/__init__.py
paxtual/check_ip.py
paxtual/commands.py
paxtual/confmscn.py
paxtual/entry_points.py
paxtual/eval_2_linkscreen.py
paxtual/functionsScreen.py
paxtual/get_wsid.py
paxtual/list_stringifyer.py
paxtual/notasync.py
paxtual/operations.py
paxtual/pass_fail_screen.py
paxtual/pass_or_fail_screen.py
paxtual/paxAPItool.py
paxtual/paxStoreChecker.py
paxtual/pax_exceptions.py
paxtual/paxterms.py
paxtual/replace_terminal_screen.py
paxtual/scan_qr.py
paxtual/scan_v2.py
paxtual/serialNoValidator.py
paxtual/submit_to_sheets.py
paxtual/textual_file_selector.py
paxtual/ti_labels_iccid.py
paxtual/tui_exceptions.py
paxtual/welcome_screen.py
paxtual/css_lib/combining_layouts.tcss
paxtual/css_lib/confirm_screen.tcss
paxtual/css_lib/group_gunctions.tcss
paxtual/css_lib/poll.tcss
paxtual/css_lib/scan_or_import_screen.tcss
paxtual/css_lib/screen01.tcss
paxtual/css_lib/singleTermDetails.tcss
paxtual/css_lib/welcom.tcss
paxtual-0.3.1.dist-info/METADATA
paxtual-0.3.1.dist-info/WHEEL
paxtual-0.3.1.dist-info/entry_points.txt
paxtual-0.3.1.dist-info/licenses/LICENSE.txt
paxtual-0.3.1.dist-info/RECORD
