Metadata-Version: 2.3
Name: paxtual
Version: 0.3.1
Author-email: Scott <fake@fake.com>
Classifier: Development Status :: 4 - Beta
Classifier: Programming Language :: Python
Classifier: Programming Language :: Python :: 3.8
Classifier: Programming Language :: Python :: 3.9
Classifier: Programming Language :: Python :: 3.10
Classifier: Programming Language :: Python :: 3.11
Classifier: Programming Language :: Python :: 3.12
Classifier: Programming Language :: Python :: 3.13
Classifier: Programming Language :: Python :: Implementation :: CPython
Classifier: Programming Language :: Python :: Implementation :: PyPy
Requires-Python: >=3.8
Requires-Dist: aiohttp
Requires-Dist: google-auth-oauthlib
Requires-Dist: gspread
Requires-Dist: openpyxl
Requires-Dist: pandas
Requires-Dist: reportlab
Requires-Dist: reportlab-qrcode
Requires-Dist: requests
Requires-Dist: textual
